materials_commons/api/LICENSE.txt
materials_commons/api/__init__.py
materials_commons/api/client.py
materials_commons/api/config.py
materials_commons/api/mc_project.py
materials_commons/api/models.py
materials_commons/api/query.py
materials_commons/api/query_params.py
materials_commons/api/requests.py
materials_commons/api/util.py
materials_commons_api-2.1.1.dist-info/LICENSE
materials_commons_api-2.1.1.dist-info/METADATA
materials_commons_api-2.1.1.dist-info/WHEEL
materials_commons_api-2.1.1.dist-info/top_level.txt
materials_commons_api-2.1.1.dist-info/RECORD
