Metadata-Version: 2.1
Name: materials-commons-api
Version: 2.1.1
Summary: API interface to Materials Commons
Home-page: https://materials-commons.github.io/materials-commons-api/html/index.html
Author: Materials Commons development team
Author-email: materials-commons-authors@umich.edu
License: MIT
Keywords: materials science mc materials-commons prisms
Platform: UNKNOWN
Classifier: Development Status :: 4 - Beta
Classifier: Intended Audience :: Developers
Classifier: Intended Audience :: Science/Research
Classifier: Topic :: Scientific/Engineering :: Information Analysis
Classifier: License :: OSI Approved :: MIT License
Classifier: Programming Language :: Python :: 3
Classifier: Programming Language :: Python :: 3.8
License-File: LICENSE
Requires-Dist: requests (>=2.32.5)
Requires-Dist: tuspy (>=1.1.0)
